{
    "events": [
        {
            "text": "President of the United States Donald Trump is injured in an assassination attempt while speaking at an election campaign rally near Butler, Pennsylvania.",
            "year": 2024
        },
        {
            "text": "After a five-day search, the body of American actress and singer Naya Rivera is recovered from Lake Piru, where she drowned in California.",
            "year": 2020
        },
        {
            "text": "Prime Minister of the United Kingdom David Cameron resigns, and is succeeded by Theresa May.",
            "year": 2016
        },
        {
            "text": "Germany wins the FIFA World Cup, defeating Argentina in the final 1–0 after extra time.",
            "year": 2014
        },
        {
            "text": "Typhoon Soulik kills at least nine people and affects more than 160 million in East China and Taiwan.",
            "year": 2013
        },
        {
            "text": "Mumbai is rocked by three bomb blasts during the evening rush hour, killing 26 and injuring 130.",
            "year": 2011
        },
        {
            "text": "United Nations Security Council Resolution 1999 is adopted, which admits South Sudan to member status of United Nations.",
            "year": 2011
        },
        {
            "text": "Battle of Wanat begins when Taliban and al-Qaeda guerrillas attack US Army and Afghan National Army troops in Afghanistan. The U.S. deaths were, at that time, the most in a single battle since the beginning of operations in 2001.",
            "year": 2008
        },
        {
            "text": "French DGSE personnel abort an operation to rescue Íngrid Betancourt from FARC rebels in Colombia, causing a political scandal when details are leaked to the press.",
            "year": 2003
        },
        {
            "text": "Space Shuttle Discovery is launched on STS-70 to deploy the TDRS-7 satellite.",
            "year": 1995
        },
        {
            "text": "Lenin Peak disaster: a 6.4-magnitude earthquake in Afghanistan triggers an avalanche on Lenin Peak, killing 43 climbers in the deadliest mountaineering disaster in history.",
            "year": 1990
        },
        {
            "text": "The Live Aid benefit concert takes place in London and Philadelphia, as well as other venues such as Moscow and Sydney.",
            "year": 1985
        },
        {
            "text": "Vice President George H. W. Bush becomes the Acting President for the day when President Ronald Reagan undergoes surgery to remove polyps from his colon.",
            "year": 1985
        },
        {
            "text": "Somalia declares war on Ethiopia, starting the Ogaden War.",
            "year": 1977
        },
        {
            "text": "New York City: Amidst a period of financial and social turmoil experiences an electrical blackout lasting nearly 24 hours that leads to widespread fires and looting.",
            "year": 1977
        },
        {
            "text": "Watergate scandal: Alexander Butterfield reveals the existence of a secret Oval Office taping system to investigators for the Senate Watergate Committee.",
            "year": 1973
        },
        {
            "text": "In an unprecedented action, British Prime Minister Harold Macmillan dismisses seven members of his Cabinet, marking the effective end of the National Liberals as a distinct force within British politics.",
            "year": 1962
        },
        {
            "text": "The Dartmouth workshop is the first conference on artificial intelligence.",
            "year": 1956
        },
        {
            "text": "Vuoristorata, one of the oldest still-operating wooden roller coasters in Europe, is opened at the Linnanmäki amusement park in Helsinki, Finland.",
            "year": 1951
        },
        {
            "text": "World War II: Montenegrins begin the Trinaestojulski ustanak (Thirteenth of July Uprising), a popular revolt against the Axis powers.",
            "year": 1941
        },
        {
            "text": "The inaugural FIFA World Cup begins in Uruguay.",
            "year": 1930
        },
        {
            "text": "The British airship R34 lands in Norfolk, England, completing the first airship return journey across the Atlantic in 182 hours of flight.",
            "year": 1919
        },
        {
            "text": "The 1913 Romanian Army cholera outbreak during the Second Balkan War starts.",
            "year": 1913
        },
        {
            "text": "Treaty of Berlin: The European powers redraw the map of the Balkans. Serbia, Montenegro and Romania become completely independent of the Ottoman Empire.",
            "year": 1878
        },
        {
            "text": "American Civil War: The New York City draft riots begin three days of rioting which will later be regarded as the worst in United States history.",
            "year": 1863
        },
        {
            "text": "In the Battle of Guaymas, Mexico, General José María Yáñez stops the French invasion led by Count Gaston de Raousset-Boulbon.",
            "year": 1854
        },
        {
            "text": "The Charleston Workhouse Slave Rebellion began in Charleston, South Carolina, United States.",
            "year": 1849
        },
        {
            "text": "Regulamentul Organic, a quasi-constitutional organic law is adopted in Wallachia, one of the two Danubian Principalities that were to become the basis of Romania.",
            "year": 1831
        },
        {
            "text": "The General Assembly's Institution, now the Scottish Church College, one of the pioneering institutions that ushered the Bengali Renaissance, is founded by Alexander Duff and Raja Ram Mohan Roy, in Calcutta, India.",
            "year": 1830
        },
        {
            "text": "The Carabinieri, the national gendarmerie of Italy, is established.",
            "year": 1814
        },
        {
            "text": "The Battle of Trippstadt between French forces and those of Prussia and Austria begins.",
            "year": 1794
        },
        {
            "text": "Journalist and French revolutionary Jean-Paul Marat is assassinated in his bathtub by Charlotte Corday, a member of the opposing political faction; Corday is guillotined four days later.",
            "year": 1793
        },
        {
            "text": "The Congress of the Confederation enacts the Northwest Ordinance establishing governing rules for the Northwest Territory. It also establishes procedures for the admission of new states and limits the expansion of slavery.",
            "year": 1787
        },
        {
            "text": "Nine Years' War: French naval forces led by Anne Hilarion de Tourville fresh from their victory at Beachy Head sail West and launch a raid on the small English town of Teignmouth leaving it devastated.",
            "year": 1690
        },
        {
            "text": "English Civil War: Battle of Roundway Down: In England, Henry Wilmot, 1st Earl of Rochester, commanding the Royalist forces, heavily defeats the Parliamentarian forces led by Sir William Waller.",
            "year": 1643
        },
        {
            "text": "Anglo–Spanish War: A convoy of English ships from the Levant Company manage to repel a fleet of eleven Spanish and Maltese galleys off the Mediterranean island of Pantelleria.",
            "year": 1586
        },
        {
            "text": "Eighty Years' War: The Siege of Haarlem ends after seven months.",
            "year": 1573
        },
        {
            "text": "Battle of Gravelines: In France, Spanish forces led by Count Lamoral of Egmont defeat the French forces of Marshal Paul de Thermes at Gravelines.",
            "year": 1558
        },
        {
            "text": "Nanjing surrenders to Zhu Di without a fight, ending the Jingnan campaign. The Jianwen Emperor disappears and his family is incarcerated.",
            "year": 1402
        },
        {
            "text": "The Livonian Order suffers its greatest defeat in the 13th century in the Battle of Durbe against the Grand Duchy of Lithuania",
            "year": 1260
        },
        {
            "text": "Coronation of Alexander III as King of Scots.",
            "year": 1249
        },
        {
            "text": "William I of Scotland, a key rebel in the Revolt of 1173–74, is captured at Alnwick by forces loyal to Henry II of England.",
            "year": 1174
        }
    ],
    "births": [
        {
            "text": "Lamine Yamal, Spanish footballer",
            "year": 2007
        },
        {
            "text": "Wyatt Oleff, American actor",
            "year": 2003
        },
        {
            "text": "Mason Teague, Australian rugby league player",
            "year": 2003
        },
        {
            "text": "Deborah Medrado, Brazilian rhythmic gymnast",
            "year": 2002
        },
        {
            "text": "Kim Sin-jin, South Korean footballer",
            "year": 2001
        },
        {
            "text": "Josh Hines-Allen, American football player",
            "year": 1997
        },
        {
            "text": "Leo Howard, American actor and martial artist",
            "year": 1997
        },
        {
            "text": "Cody Bellinger, American baseball player",
            "year": 1995
        },
        {
            "text": "Dante Exum, Australian basketball player",
            "year": 1995
        },
        {
            "text": "Dan Bentley, English footballer",
            "year": 1993
        },
        {
            "text": "Rich the Kid, American rapper",
            "year": 1992
        },
        {
            "text": "Elise Matthysen, Belgian swimmer",
            "year": 1992
        },
        {
            "text": "Tyler Skaggs, American baseball player (died 2019)",
            "year": 1991
        },
        {
            "text": "Kieran Foran, New Zealand rugby league player",
            "year": 1990
        },
        {
            "text": "Eduardo Salvio, Argentinian footballer",
            "year": 1990
        },
        {
            "text": "Leon Bridges, American soul singer, songwriter and record producer",
            "year": 1989
        },
        {
            "text": "Charis Giannopoulos, Greek basketball player",
            "year": 1989
        },
        {
            "text": "Marcos Paulo Gelmini Gomes, Brazilian-Italian footballer",
            "year": 1988
        },
        {
            "text": "Colton Haynes, American actor, model and singer",
            "year": 1988
        },
        {
            "text": "DJ LeMahieu, American baseball player",
            "year": 1988
        },
        {
            "text": "Steven R. McQueen, American actor and model",
            "year": 1988
        },
        {
            "text": "Raúl Spank, German high jumper",
            "year": 1988
        },
        {
            "text": "Tulisa, English singer-songwriter and actress",
            "year": 1988
        },
        {
            "text": "Trell Kimmons, American sprinter",
            "year": 1985
        },
        {
            "text": "Guillermo Ochoa, Mexican footballer",
            "year": 1985
        },
        {
            "text": "Charlotte Dujardin, English equestrian",
            "year": 1985
        },
        {
            "text": "Abdallah El Said, Egyptian footballer",
            "year": 1985
        },
        {
            "text": "Ida Maria, Norwegian singer-songwriter and guitarist",
            "year": 1984
        },
        {
            "text": "Faf du Plessis, South African professional cricketer",
            "year": 1984
        },
        {
            "text": "Kristof Beyens, Belgian sprinter",
            "year": 1983
        },
        {
            "text": "Marco Pomante, Italian footballer",
            "year": 1983
        },
        {
            "text": "Liu Xiang, Chinese hurdler",
            "year": 1983
        },
        {
            "text": "Shin-Soo Choo, South Korean baseball player",
            "year": 1982
        },
        {
            "text": "Simon Clist, English footballer",
            "year": 1982
        },
        {
            "text": "Dominic Isaacs, South African footballer",
            "year": 1982
        },
        {
            "text": "Nick Kenny, Australian rugby league player",
            "year": 1982
        },
        {
            "text": "Yadier Molina, Puerto Rican baseball player",
            "year": 1982
        },
        {
            "text": "Ágnes Kovács, Hungarian swimmer",
            "year": 1981
        },
        {
            "text": "Mirco Lorenzetto, Italian cyclist",
            "year": 1981
        },
        {
            "text": "Craig Bellamy, Welsh footballer",
            "year": 1979
        },
        {
            "text": "Daniel Díaz, Argentinian footballer",
            "year": 1979
        },
        {
            "text": "Libuše Průšová, Czech tennis player",
            "year": 1979
        },
        {
            "text": "Lucinda Ruh, Swiss figure skater and coach",
            "year": 1979
        },
        {
            "text": "Ryan Ludwick, American baseball player",
            "year": 1978
        },
        {
            "text": "Prodromos Nikolaidis, Greek basketball player",
            "year": 1978
        },
        {
            "text": "Chris Horn, American football player",
            "year": 1977
        },
        {
            "text": "Sheldon Souray, Canadian ice hockey player",
            "year": 1976
        },
        {
            "text": "Diego Spotorno, Ecuadorian actor",
            "year": 1975
        },
        {
            "text": "Mariada Pieridi, Cypriot singer-songwriter",
            "year": 1975
        },
        {
            "text": "Deborah Cox, Canadian singer-songwriter and actress",
            "year": 1974
        },
        {
            "text": "Jarno Trulli, Italian race car driver",
            "year": 1974
        },
        {
            "text": "Sean Waltman, American professional wrestler",
            "year": 1972
        },
        {
            "text": "MF Doom, English-American rapper (died 2020)",
            "year": 1971
        },
        {
            "text": "Mark Neeld, Australian footballer and coach",
            "year": 1971
        },
        {
            "text": "Andrei Tivontchik, German pole vaulter and trainer",
            "year": 1970
        },
        {
            "text": "Brad Godden, Australian rugby league player",
            "year": 1969
        },
        {
            "text": "Ken Jeong, American actor, comedian, and physician",
            "year": 1969
        },
        {
            "text": "Oleg Serebrian, Moldovan political scientist and politician",
            "year": 1969
        },
        {
            "text": "Richard Marles, Australian lawyer and politician, 50th Australian Minister for Trade and Investment",
            "year": 1967
        },
        {
            "text": "Mark McGowan, Australian politician, 30th Premier of Western Australia",
            "year": 1967
        },
        {
            "text": "Gerald Levert, American R&B singer-songwriter, producer, and actor (died 2006)",
            "year": 1966
        },
        {
            "text": "Natalia Luis-Bassa, Venezuelan-English conductor and educator",
            "year": 1966
        },
        {
            "text": "Eileen Ivers, American fiddler",
            "year": 1965
        },
        {
            "text": "Akina Nakamori, Japanese singer and actress",
            "year": 1965
        },
        {
            "text": "Colin van der Voort, Australian rugby league player",
            "year": 1965
        },
        {
            "text": "Charlie Hides, American drag queen and comedian",
            "year": 1964
        },
        {
            "text": "Paul Thorn, American singer-songwriter and guitarist",
            "year": 1964
        },
        {
            "text": "Parker Bohn III, American bowler",
            "year": 1963
        },
        {
            "text": "Neal Foulds, English snooker player and sportscaster",
            "year": 1963
        },
        {
            "text": "Kenny Johnson, American actor, producer, and model",
            "year": 1963
        },
        {
            "text": "Tom Kenny, American voice actor and screenwriter",
            "year": 1962
        },
        {
            "text": "Rhonda Vincent, American singer-songwriter and mandolin player",
            "year": 1962
        },
        {
            "text": "Tahira Asif, Pakistani politician (died 2014)",
            "year": 1961
        },
        {
            "text": "Anders Jarryd, Swedish tennis player",
            "year": 1961
        },
        {
            "text": "Khalid Mahmood, Pakistani-English engineer and politician",
            "year": 1961
        },
        {
            "text": "Stelios Manolas, Greek footballer and manager",
            "year": 1961
        },
        {
            "text": "Tim Watson, Australian footballer, coach, and journalist",
            "year": 1961
        },
        {
            "text": "Robert Abraham, American football player",
            "year": 1960
        },
        {
            "text": "Ian Hislop, Welsh-English journalist and screenwriter",
            "year": 1960
        },
        {
            "text": "Curtis Rouse, American football player (died 2013)",
            "year": 1960
        },
        {
            "text": "Richard Leman, English field hockey player",
            "year": 1959
        },
        {
            "text": "Fuziah Salleh, Malaysian politician",
            "year": 1959
        },
        {
            "text": "Thierry Boutsen, Belgian race car driver and businessman",
            "year": 1957
        },
        {
            "text": "Cameron Crowe, American director, producer, and screenwriter",
            "year": 1957
        },
        {
            "text": "Mark Mendoza, American bass player and songwriter",
            "year": 1956
        },
        {
            "text": "Michael Spinks, American boxer",
            "year": 1956
        },
        {
            "text": "Ray Bright, Australian cricketer",
            "year": 1954
        },
        {
            "text": "Louise Mandrell, American singer-songwriter and actress",
            "year": 1954
        },
        {
            "text": "Gil Birmingham, American actor",
            "year": 1953
        },
        {
            "text": "David Thompson, American basketball player",
            "year": 1953
        },
        {
            "text": "Rob Bishop, American educator and politician",
            "year": 1951
        },
        {
            "text": "Didi Conn, American actress and singer",
            "year": 1951
        },
        {
            "text": "George Nelson, American astronomer and astronaut",
            "year": 1950
        },
        {
            "text": "Ma Ying-jeou, Hong Kong-Taiwanese commander and politician, 12th President of the Republic of China",
            "year": 1950
        },
        {
            "text": "Jurelang Zedkaia, Marshallese politician, 5th President of the Marshall Islands (died 2015)",
            "year": 1950
        },
        {
            "text": "Bryan Murray, Irish actor",
            "year": 1949
        },
        {
            "text": "Catherine Breillat, French director and screenwriter",
            "year": 1948
        },
        {
            "text": "Tony Kornheiser, American television sports talk show host and former sportswriter",
            "year": 1948
        },
        {
            "text": "Bob Kauffman, American basketball player and coach (died 2015)",
            "year": 1946
        },
        {
            "text": "Cheech Marin, American actor and comedian",
            "year": 1946
        },
        {
            "text": "Ashley Mallett, Australian cricketer and author (died 2021)",
            "year": 1945
        },
        {
            "text": "Eric Freeman, Australian cricketer (died 2020)",
            "year": 1944
        },
        {
            "text": "Cyril Knowles, English footballer and manager (died 1991)",
            "year": 1944
        },
        {
            "text": "Ernő Rubik, Hungarian game designer, architect, and educator, invented the Rubik's Cube",
            "year": 1944
        },
        {
            "text": "Chris Serle, English journalist and actor (died 2024)",
            "year": 1943
        },
        {
            "text": "Harrison Ford, American actor and producer",
            "year": 1942
        },
        {
            "text": "Roger McGuinn, American singer-songwriter and guitarist",
            "year": 1942
        },
        {
            "text": "Grahame Corling, Australian cricketer",
            "year": 1941
        },
        {
            "text": "Robert Forster, American actor and producer (died 2019)",
            "year": 1941
        },
        {
            "text": "Ehud Manor, Israeli songwriter and translator (died 2005)",
            "year": 1941
        },
        {
            "text": "Jacques Perrin, French actor, director, and producer (died 2022)",
            "year": 1941
        },
        {
            "text": "Tom Lichtenberg, American football player and coach (died 2013)",
            "year": 1940
        },
        {
            "text": "Paul Prudhomme, American chef and author (died 2015)",
            "year": 1940
        },
        {
            "text": "Patrick Stewart, English actor, director, and producer",
            "year": 1940
        },
        {
            "text": "Lambert Jackson Woodburne, South African admiral (died 2013)",
            "year": 1939
        },
        {
            "text": "Ghillean Prance, English botanist and ecologist",
            "year": 1937
        },
        {
            "text": "Albert Ayler, American saxophonist and composer (died 1970)",
            "year": 1936
        },
        {
            "text": "Jack Kemp, American football player and politician, 9th United States Secretary of Housing and Urban Development (died 2009)",
            "year": 1935
        },
        {
            "text": "Earl Lovelace, Trinidadian journalist, author, and playwright",
            "year": 1935
        },
        {
            "text": "Kurt Westergaard, Danish cartoonist (died 2021)",
            "year": 1935
        },
        {
            "text": "Peter Gzowski, Canadian journalist and academic (died 2002)",
            "year": 1934
        },
        {
            "text": "Gordon Lee, English footballer and manager (died 2022)",
            "year": 1934
        },
        {
            "text": "Wole Soyinka, Nigerian author, poet, and playwright, Nobel Prize laureate",
            "year": 1934
        },
        {
            "text": "Aleksei Yeliseyev, Russian engineer and astronaut",
            "year": 1934
        },
        {
            "text": "David Storey, English author, playwright, and screenwriter (died 2017)",
            "year": 1933
        },
        {
            "text": "Piero Manzoni, Italian artist (died 1963)",
            "year": 1933
        },
        {
            "text": "Hubert Reeves, Canadian-French astrophysicist and author (died 2023)",
            "year": 1932
        },
        {
            "text": "Per Nørgård, Danish composer and music theorist (died 2025)",
            "year": 1932
        },
        {
            "text": "Frank Ramsey, American basketball player and coach (died 2018)",
            "year": 1931
        },
        {
            "text": "Sam Greenlee, American author and poet (died 2014)",
            "year": 1930
        },
        {
            "text": "Naomi Shemer, Israeli singer-songwriter (died 2004)",
            "year": 1930
        },
        {
            "text": "Sofia Muratova, Russian gymnast (died 2006)",
            "year": 1929
        },
        {
            "text": "Svein Ellingsen, Norwegian visual artist and hymnist (died 2020)",
            "year": 1929
        },
        {
            "text": "Bob Crane, American actor (died 1978)",
            "year": 1928
        },
        {
            "text": "Sven Davidson, Swedish-American tennis player (died 2008)",
            "year": 1928
        },
        {
            "text": "Johnny Gilbert, American game show host and announcer",
            "year": 1928
        },
        {
            "text": "Al Rex, American musician (died 2020)",
            "year": 1928
        },
        {
            "text": "Simone Veil, French lawyer and politician, President of the European Parliament (died 2017)",
            "year": 1927
        },
        {
            "text": "Ian Reed, Australian discus thrower (died 2020)",
            "year": 1927
        },
        {
            "text": "Robert H. Justman, American director, producer, and production manager (died 2008)",
            "year": 1926
        },
        {
            "text": "T. Loren Christianson, American politician (died 2019)",
            "year": 1926
        },
        {
            "text": "Thomas Clark, American politician (died 2020)",
            "year": 1926
        },
        {
            "text": "Suzanne Zimmerman, American competition swimmer and Olympic medalist (died 2021)",
            "year": 1925
        },
        {
            "text": "Huang Zongying, Chinese actress and writer (died 2020)",
            "year": 1925
        },
        {
            "text": "Ashley Bryan, American children's book author and illustrator (died 2022)",
            "year": 1923
        },
        {
            "text": "Leslie Brooks, American actress (died 2011)",
            "year": 1922
        },
        {
            "text": "Anker Jørgensen, Danish trade union leader and politician, 16th Prime Minister of Denmark (died 2016)",
            "year": 1922
        },
        {
            "text": "Helmy Afify Abd El-Bar, Egyptian military commander (died 2011)",
            "year": 1922
        },
        {
            "text": "Ken Mosdell, Canadian ice hockey player (died 2006)",
            "year": 1922
        },
        {
            "text": "Ernest Gold, Austrian-American composer and conductor (died 1999)",
            "year": 1921
        },
        {
            "text": "Hau Pei-tsun, 13th Premier of the Republic of China (died 2020)",
            "year": 1919
        },
        {
            "text": "William F. Quinn, American lawyer (died 2006)",
            "year": 1919
        },
        {
            "text": "Alberto Ascari, Italian race car driver (died 1955)",
            "year": 1918
        },
        {
            "text": "Ronald Bladen, American painter and sculptor (died 1988)",
            "year": 1918
        },
        {
            "text": "Marcia Brown, American author and illustrator (died 2015)",
            "year": 1918
        },
        {
            "text": "Kaoru Ishikawa, Japanese author and educator (died 1989)",
            "year": 1915
        },
        {
            "text": "Dave Garroway, American journalist and television personality (died 1982)",
            "year": 1913
        },
        {
            "text": "Mærsk Mc-Kinney Møller, Danish businessman (died 2012)",
            "year": 1913
        },
        {
            "text": "Bob Steele, American radio personality (died 2002)",
            "year": 1911
        },
        {
            "text": "Lien Gisolf, Dutch high jumper (died 1993)",
            "year": 1910
        },
        {
            "text": "Loren Pope, American journalist and author (died 2008)",
            "year": 1910
        },
        {
            "text": "Souphanouvong, 1st President of Laos (died 1995)",
            "year": 1909
        },
        {
            "text": "Dorothy Round, English tennis player (died 1982)",
            "year": 1908
        },
        {
            "text": "Tim Spencer, American country & western singer-songwriter and actor (died 1974)",
            "year": 1908
        },
        {
            "text": "George Weller, American author, playwright, and journalist (died 2002)",
            "year": 1907
        },
        {
            "text": "Alfredo M. Santos, Filipino general (died 1990)",
            "year": 1905
        },
        {
            "text": "Eugenio Pagnini, Italian modern pentathlete (died 1993)",
            "year": 1905
        },
        {
            "text": "Magda Foy, American child actress (died 2000)",
            "year": 1905
        },
        {
            "text": "Kenneth Clark, English historian and author (died 1983)",
            "year": 1903
        },
        {
            "text": "Eric Portman, English actor (died 1969)",
            "year": 1901
        },
        {
            "text": "George Lewis, American clarinet player and songwriter (died 1969)",
            "year": 1900
        },
        {
            "text": "Julius Schreck, German commander (died 1936)",
            "year": 1898
        },
        {
            "text": "Ivan Triesault, Estonian-born American actor (died 1980)",
            "year": 1898
        },
        {
            "text": "Mordecai Ardon, Israeli painter and educator (died 1992)",
            "year": 1896
        },
        {
            "text": "Sidney Blackmer, American actor (died 1973)",
            "year": 1895
        },
        {
            "text": "Isaac Babel, Russian short story writer, journalist, and playwright (died 1940)",
            "year": 1894
        },
        {
            "text": "Léo-Pol Morin, Canadian pianist, composer, and educator (died 1941)",
            "year": 1892
        },
        {
            "text": "Jonni Myyrä, Finnish-American discus and javelin thrower (died 1955)",
            "year": 1892
        },
        {
            "text": "Emma Asson, Estonian educator and politician (died 1965)",
            "year": 1889
        },
        {
            "text": "Stan Coveleski, American baseball player (died 1984)",
            "year": 1889
        },
        {
            "text": "Father Edward J. Flanagan, founder of Boys Town (died 1948)",
            "year": 1886
        },
        {
            "text": "Yrjö Saarela, Finnish wrestler and coach (died 1951)",
            "year": 1884
        },
        {
            "text": "Robert Henry Mathews, Australian linguist and missionary (died 1970)",
            "year": 1877
        },
        {
            "text": "John Jacob Astor IV, American colonel and businessman (died 1912)",
            "year": 1864
        },
        {
            "text": "Margaret Murray, British archaeologist, anthropologist, historian, and folklorist (died 1963)",
            "year": 1863
        },
        {
            "text": "Sidney Webb, 1st Baron Passfield, English economist and politician, Secretary of State for the Colonies (died 1947)",
            "year": 1859
        },
        {
            "text": "Stewart Culin, American ethnographer and author (died 1929)",
            "year": 1858
        },
        {
            "text": "Otto Wagner, Austrian architect, designed the Austrian Postal Savings Bank and Karlsplatz Stadtbahn Station (died 1918)",
            "year": 1841
        },
        {
            "text": "Arthur Böttcher, German pathologist and anatomist (died 1889)",
            "year": 1831
        },
        {
            "text": "Nathan Bedford Forrest, American general and first Grand Wizard of the Ku Klux Klan (died 1877)",
            "year": 1821
        },
        {
            "text": "John Clare, English poet and author (died 1864)",
            "year": 1793
        },
        {
            "text": "Alexander Balashov, Russian general and politician, Russian Minister of Police (died 1837)",
            "year": 1770
        },
        {
            "text": "István Pauli, Hungarian-Slovene priest and poet (died 1829)",
            "year": 1760
        },
        {
            "text": "Thomas Rowlandson, English artist and caricaturist (died 1827)",
            "year": 1756
        },
        {
            "text": "Robert Calder, Scottish-English admiral (died 1818)",
            "year": 1745
        },
        {
            "text": "Ferdinand III, Holy Roman Emperor (died 1657)",
            "year": 1608
        },
        {
            "text": "Wenceslaus Hollar, Czech-English painter and illustrator (died 1677)",
            "year": 1607
        },
        {
            "text": "Roland Fréart de Chambray (died 1676)",
            "year": 1606
        },
        {
            "text": "Pope Clement X (died 1676)",
            "year": 1590
        },
        {
            "text": "Arthur Dee, English physician and chemist (died 1651)",
            "year": 1579
        },
        {
            "text": "John Dee, English-Welsh mathematician, astronomer, and astrologer (died 1609)",
            "year": 1527
        },
        {
            "text": "Giulio d'Este, illegitimate son of Italian noble (died 1561)",
            "year": 1478
        },
        {
            "text": "Francesco Armellini Pantalassi de' Medici, Catholic cardinal (died 1528)",
            "year": 1470
        }
    ],
    "deaths": [
        {
            "text": "Shannen Doherty, American actress (born 1971)",
            "year": 2024
        },
        {
            "text": "Ruth Hesse, German opera singer (born 1936)",
            "year": 2024
        },
        {
            "text": "Richard Simmons, American fitness personality and public figure (born 1948)",
            "year": 2024
        },
        {
            "text": "Chino Trinidad, Filipino sports journalist and executive (born 1967)",
            "year": 2024
        },
        {
            "text": "Thomas Matthew Crooks, American student, known for attempting to assassinate former US President Donald Trump (born 2003)",
            "year": 2024
        },
        {
            "text": "Naomi Pomeroy, American Chef and Restaurateur (born 1974)",
            "year": 2024
        },
        {
            "text": "Grant Imahara, American electrical engineer, roboticist, and television host (born 1970)",
            "year": 2020
        },
        {
            "text": "Zindzi Mandela, South African politician, diplomat, and third daughter of Nelson Mandela (born 1960)",
            "year": 2020
        },
        {
            "text": "Liu Xiaobo, Chinese literary critic, human rights activist (born 1955)",
            "year": 2017
        },
        {
            "text": "Philipp Mißfelder, German historian and politician (born 1979)",
            "year": 2015
        },
        {
            "text": "Martin Litchfield West, English scholar, author, and academic (born 1927)",
            "year": 2015
        },
        {
            "text": "Thomas Berger, American author and playwright (born 1924)",
            "year": 2014
        },
        {
            "text": "Alfred de Grazia, American political scientist, author, and academic (born 1919)",
            "year": 2014
        },
        {
            "text": "Nadine Gordimer, South African novelist, short story writer, and activist, Nobel Prize laureate (born 1923)",
            "year": 2014
        },
        {
            "text": "Jeff Leiding, American football player (born 1961)",
            "year": 2014
        },
        {
            "text": "Lorin Maazel, French-American violinist, composer, and conductor (born 1930)",
            "year": 2014
        },
        {
            "text": "Leonard Garment,  American lawyer and public servant, 14th White House Counsel (born 1924)",
            "year": 2013
        },
        {
            "text": "Henri Julien, French race car driver (born 1927)",
            "year": 2013
        },
        {
            "text": "Cory Monteith, Canadian actor and singer (born 1982)",
            "year": 2013
        },
        {
            "text": "Ottavio Quattrocchi, Italian businessman (born 1938)",
            "year": 2013
        },
        {
            "text": "Vernon B. Romney, American lawyer and politician, 14th Attorney General of Utah (born 1924)",
            "year": 2013
        },
        {
            "text": "Marc Simont, French-American author and illustrator (born 1915)",
            "year": 2013
        },
        {
            "text": "Warren Jabali, American basketball player (born 1946)",
            "year": 2012
        },
        {
            "text": "Jerzy Kulej, Polish boxer and politician (born 1940)",
            "year": 2012
        },
        {
            "text": "Richard D. Zanuck, American film producer (born 1934)",
            "year": 2012
        },
        {
            "text": "Allan Jeans, Australian footballer and coach (born 1933)",
            "year": 2011
        },
        {
            "text": "Manohari Singh, Indian saxophonist and composer (born 1931)",
            "year": 2010
        },
        {
            "text": "George Steinbrenner, American businessman (born 1930)",
            "year": 2010
        },
        {
            "text": "Bronisław Geremek, Polish historian and politician, Polish Minister of Foreign Affairs (born 1932)",
            "year": 2008
        },
        {
            "text": "Michael Reardon, American mountaineer (born 1965)",
            "year": 2007
        },
        {
            "text": "Red Buttons, American actor (born 1919)",
            "year": 2006
        },
        {
            "text": "Robert E. Ogren, American zoologist (born 1922)",
            "year": 2005
        },
        {
            "text": "Compay Segundo, Cuban singer-songwriter and guitarist (born 1907)",
            "year": 2003
        },
        {
            "text": "Jan Karski, Polish-American activist and academic (born 1914)",
            "year": 2000
        },
        {
            "text": "Konstantinos Kollias, Greek general and politician, 168th Prime Minister of Greece (born 1901)",
            "year": 1999
        },
        {
            "text": "Miguel Ángel Blanco, Spanish politician (born 1968)",
            "year": 1997
        },
        {
            "text": "Pandro S. Berman, American director, producer, and production manager (born 1905)",
            "year": 1996
        },
        {
            "text": "Godtfred Kirk Christiansen, Danish businessman (born 1920)",
            "year": 1995
        },
        {
            "text": "Davey Allison, American race car driver (born 1961)",
            "year": 1993
        },
        {
            "text": "Gabrielle Roy, Canadian engineer and author (born 1909)",
            "year": 1983
        },
        {
            "text": "Martin Hurson Irish Republican Hunger Striker",
            "year": 1981
        },
        {
            "text": "Seretse Khama, Botswana lawyer and politician, 1st President of Botswana (born 1921)",
            "year": 1980
        },
        {
            "text": "Ludwig Merwart, Austrian painter and illustrator (born 1913)",
            "year": 1979
        },
        {
            "text": "Frederick Hawksworth, English engineer (born 1884)",
            "year": 1976
        },
        {
            "text": "Joachim Peiper, German SS officer (born 1915)",
            "year": 1976
        },
        {
            "text": "Patrick Blackett, Baron Blackett, English physicist and academic, Nobel Prize laureate (born 1897)",
            "year": 1974
        },
        {
            "text": "Willy Fritsch, German actor and screenwriter (born 1901)",
            "year": 1973
        },
        {
            "text": "Leslie Groves, American general and engineer (born 1896)",
            "year": 1970
        },
        {
            "text": "Sheng Shicai, Chinese warlord (born 1895)",
            "year": 1970
        },
        {
            "text": "Tom Simpson, English cyclist (born 1937)",
            "year": 1967
        },
        {
            "text": "Photis Kontoglou, Greek painter, illustrator and writer (born 1895)",
            "year": 1965
        },
        {
            "text": "Joy Davidman, American-English poet and author (born 1915)",
            "year": 1960
        },
        {
            "text": "Frida Kahlo, Mexican painter and educator (born 1907)",
            "year": 1954
        },
        {
            "text": "Arnold Schoenberg, Austrian-American composer and painter (born 1874)",
            "year": 1951
        },
        {
            "text": "Walt Kuhn, American painter and academic (born 1877)",
            "year": 1949
        },
        {
            "text": "Alfred Stieglitz, American photographer and curator (born 1864)",
            "year": 1946
        },
        {
            "text": "Alla Nazimova, Russian-American actress, producer, and screenwriter (born 1879)",
            "year": 1945
        },
        {
            "text": "Ilmar Raud, Estonian chess player (born 1913)",
            "year": 1941
        },
        {
            "text": "Kojo Tovalou Houénou, Beninese lawyer and politician (born 1887)",
            "year": 1936
        },
        {
            "text": "Mary E. Byrd, American astronomer and academic (born 1849)",
            "year": 1934
        },
        {
            "text": "Mimar Kemaleddin Bey, Turkish architect and academic, designed the Tayyare Apartments (born 1870)",
            "year": 1927
        },
        {
            "text": "Martin Dies Sr., American journalist and politician (born 1870)",
            "year": 1922
        },
        {
            "text": "Gabriel Lippmann, Luxembourger physicist and academic, Nobel Prize laureate (born 1845)",
            "year": 1921
        },
        {
            "text": "Allan McLean, Scottish-Australian politician, 19th Premier of Victoria (born 1840)",
            "year": 1911
        },
        {
            "text": "Henrik Sillem, Dutch target shooter and jurist (born 1866)",
            "year": 1907
        },
        {
            "text": "August Kekulé, German chemist and academic (born 1829)",
            "year": 1896
        },
        {
            "text": "They Even Fear His Horses, American tribal chief (born 1836)",
            "year": 1893
        },
        {
            "text": "John C. Frémont, American general and politician, 5th Territorial Governor of Arizona (born 1813)",
            "year": 1890
        },
        {
            "text": "Johann Voldemar Jannsen, Estonian journalist and poet (born 1819)",
            "year": 1890
        },
        {
            "text": "Robert Hamerling, Austrian author, poet, and playwright (born 1830)",
            "year": 1889
        },
        {
            "text": "John C. Pemberton, American general (born 1814)",
            "year": 1881
        },
        {
            "text": "Henry Benedict Stuart, Italian cardinal, pretender to the British throne and last member of the House of Stuart  (born 1725)",
            "year": 1807
        },
        {
            "text": "Jean-Paul Marat, Swiss-French physician, scientist and theorist (born 1743)",
            "year": 1793
        },
        {
            "text": "Victor de Riqueti, marquis de Mirabeau, French economist and academic (born 1715)",
            "year": 1789
        },
        {
            "text": "James Bradley, English priest and astronomer (born 1693)",
            "year": 1762
        },
        {
            "text": "Edward Braddock, Scottish general (born 1695)",
            "year": 1755
        },
        {
            "text": "Arthur Capell, 1st Earl of Essex, English politician, Lord Lieutenant of Ireland (born 1631)",
            "year": 1683
        },
        {
            "text": "Caspar Bartholin the Elder, Swedish physician and theologian (born 1585)",
            "year": 1629
        },
        {
            "text": "Robert Shirley, English soldier and diplomat (born 1581)",
            "year": 1628
        },
        {
            "text": "Robert Sidney, 1st Earl of Leicester, English politician (born 1563)",
            "year": 1626
        },
        {
            "text": "Albert VII, archduke of Austria (born 1559)",
            "year": 1621
        },
        {
            "text": "Adam Wenceslaus, duke of Cieszyn (born 1574)",
            "year": 1617
        },
        {
            "text": "John Wallop, English soldier and diplomat (born 1490)",
            "year": 1551
        },
        {
            "text": "Afonso, Portuguese prince (born 1475)",
            "year": 1491
        },
        {
            "text": "Peter Parler, German architect, designed St. Vitus Cathedral and Charles Bridge (born 1330)",
            "year": 1399
        },
        {
            "text": "Bertrand du Guesclin, French nobleman and knight (born 1320)",
            "year": 1380
        },
        {
            "text": "Bartolus de Saxoferrato Italian academic and jurist (born 1313)",
            "year": 1357
        },
        {
            "text": "Hubert Walter, English archbishop and politician, Lord Chancellor of The United Kingdom (born 1160)",
            "year": 1205
        },
        {
            "text": "Rashi, French rabbi and commentator (born 1040)",
            "year": 1105
        },
        {
            "text": "Henry II, Holy Roman Emperor (born 973)",
            "year": 1024
        },
        {
            "text": "Gunther, margrave of Merseburg",
            "year": 982
        },
        {
            "text": "Henry I, bishop of Augsburg",
            "year": 982
        },
        {
            "text": "Pandulf II, Lombard prince",
            "year": 982
        },
        {
            "text": "Landulf IV, Lombard prince",
            "year": 982
        },
        {
            "text": "Abu'l-Qasim, Kalbid emir of Sicily",
            "year": 982
        },
        {
            "text": "Leo VII, pope of the Catholic Church",
            "year": 939
        },
        {
            "text": "Huang Chao, Chinese rebel leader (born 835)",
            "year": 884
        },
        {
            "text": "Wu Yuanheng, Chinese poet and politician (born 758)",
            "year": 815
        },
        {
            "text": "Rui Zong, Chinese emperor (born 662)",
            "year": 716
        },
        {
            "text": "John III, pope of the Catholic Church",
            "year": 574
        }
    ],
    "metadata": {
        "current_date": "July 13, 2025",
        "short_date": "Jul 13",
        "language": {
            "events": "Events",
            "deaths": "Deaths",
            "births": "Births",
            "b": "b",
            "d": "d",
            "title": "This Day in History (Wikipedia)"
        },
        "events": [
            9,
            24,
            25,
            20,
            21,
            38,
            14,
            17,
            36,
            5
        ],
        "births": [
            102,
            29,
            54,
            133
        ],
        "deaths": [
            50,
            21,
            16,
            20
        ]
    }
}