[{"position": 1, "driver_name": "Justin Allgaier", "points": 806, "points_earned": 50, "playoff_points": 806, "playoff_rank": 1, "bonus_points": 0, "delta_next": 0, "delta_leader": 0, "delta_leader_playoff": 0, "delta_chase": -1, "starts": 22, "poles": 0, "wins": 2, "stage_1_wins": 7, "stage_2_wins": 6, "stage_3_wins": 0, "playoff_race_wins": 0, "playoff_stage_wins": 0, "top_5": 7, "top_10": 14, "laps_led": 570, "dnf": 4, "winnings": 0.0, "driver_id": 34, "driver_first_name": "Justin", "driver_last_name": "Allgaier", "driver_suffix": "", "car_no": "7", "manufacturer": "Chevrolet", "delta_playoff": 0, "projected_playoff_points": 2038, "stage_points": 256, "is_clinch": true}, {"position": 3, "driver_name": "Chandler Smith", "points": 731, "points_earned": 47, "playoff_points": 731, "playoff_rank": 2, "bonus_points": 0, "delta_next": -42, "delta_leader": -75, "delta_leader_playoff": 0, "delta_chase": -1, "starts": 22, "poles": 1, "wins": 2, "stage_1_wins": 3, "stage_2_wins": 2, "stage_3_wins": 0, "playoff_race_wins": 0, "playoff_stage_wins": 0, "top_5": 8, "top_10": 12, "laps_led": 418, "dnf": 2, "winnings": 0.0, "driver_id": 4312, "driver_first_name": "Chandler", "driver_last_name": "Smith", "driver_suffix": "", "car_no": "81", "manufacturer": "Toyota", "delta_playoff": 0, "projected_playoff_points": 2023, "stage_points": 189, "is_clinch": true}, {"position": 4, "driver_name": "Austin Hill", "points": 704, "points_earned": 6, "playoff_points": 704, "playoff_rank": 3, "bonus_points": 0, "delta_next": -27, "delta_leader": -102, "delta_leader_playoff": 0, "delta_chase": -1, "starts": 22, "poles": 1, "wins": 2, "stage_1_wins": 0, "stage_2_wins": 3, "stage_3_wins": 0, "playoff_race_wins": 0, "playoff_stage_wins": 0, "top_5": 8, "top_10": 13, "laps_led": 139, "dnf": 2, "winnings": 0.0, "driver_id": 4133, "driver_first_name": "Austin", "driver_last_name": "Hill", "driver_suffix": "", "car_no": "21", "manufacturer": "Chevrolet", "delta_playoff": 0, "projected_playoff_points": 2020, "stage_points": 165, "is_clinch": true}, {"position": 2, "driver_name": "Cole Custer", "points": 773, "points_earned": 5, "playoff_points": 773, "playoff_rank": 4, "bonus_points": 0, "delta_next": -33, "delta_leader": -33, "delta_leader_playoff": 0, "delta_chase": -1, "starts": 22, "poles": 3, "wins": 1, "stage_1_wins": 0, "stage_2_wins": 3, "stage_3_wins": 0, "playoff_race_wins": 0, "playoff_stage_wins": 0, "top_5": 9, "top_10": 16, "laps_led": 472, "dnf": 3, "winnings": 0.0, "driver_id": 4104, "driver_first_name": "Cole", "driver_last_name": "Custer", "driver_suffix": "", "car_no": "00", "manufacturer": "Ford", "delta_playoff": 0, "projected_playoff_points": 2018, "stage_points": 184, "is_clinch": false}, {"position": 12, "driver_name": "Shane Van Gisbergen", "points": 532, "points_earned": 12, "playoff_points": 532, "playoff_rank": 5, "bonus_points": 0, "delta_next": -29, "delta_leader": -274, "delta_leader_playoff": 0, "delta_chase": -1, "starts": 22, "poles": 2, "wins": 3, "stage_1_wins": 2, "stage_2_wins": 0, "stage_3_wins": 0, "playoff_race_wins": 0, "playoff_stage_wins": 0, "top_5": 5, "top_10": 6, "laps_led": 79, "dnf": 2, "winnings": 0.0, "driver_id": 4469, "driver_first_name": "Shane", "driver_last_name": "Van Gisbergen", "driver_suffix": "", "car_no": "97", "manufacturer": "Chevrolet", "delta_playoff": 0, "projected_playoff_points": 2017, "stage_points": 51, "is_clinch": true}, {"position": 6, "driver_name": "Riley Herbst", "points": 665, "points_earned": 42, "playoff_points": 665, "playoff_rank": 6, "bonus_points": 0, "delta_next": -9, "delta_leader": -141, "delta_leader_playoff": 0, "delta_chase": -1, "starts": 22, "poles": 0, "wins": 1, "stage_1_wins": 1, "stage_2_wins": 1, "stage_3_wins": 0, "playoff_race_wins": 0, "playoff_stage_wins": 0, "top_5": 5, "top_10": 10, "laps_led": 80, "dnf": 5, "winnings": 0.0, "driver_id": 4269, "driver_first_name": "Riley", "driver_last_name": "Herbst", "driver_suffix": "", "car_no": "98", "manufacturer": "Ford", "delta_playoff": 0, "projected_playoff_points": 2012, "stage_points": 176, "is_clinch": true}, {"position": 8, "driver_name": "Jesse Love", "points": 620, "points_earned": 16, "playoff_points": 620, "playoff_rank": 7, "bonus_points": 0, "delta_next": -34, "delta_leader": -186, "delta_leader_playoff": 0, "delta_chase": -1, "starts": 22, "poles": 3, "wins": 1, "stage_1_wins": 3, "stage_2_wins": 1, "stage_3_wins": 0, "playoff_race_wins": 0, "playoff_stage_wins": 0, "top_5": 5, "top_10": 9, "laps_led": 280, "dnf": 1, "winnings": 0.0, "driver_id": 4463, "driver_first_name": "Jesse", "driver_last_name": "Love", "driver_suffix": "", "car_no": "2", "manufacturer": "Chevrolet", "delta_playoff": 0, "projected_playoff_points": 2012, "stage_points": 111, "is_clinch": true}, {"position": 13, "driver_name": "Sam Mayer", "points": 527, "points_earned": 24, "playoff_points": 527, "playoff_rank": 8, "bonus_points": 0, "delta_next": -5, "delta_leader": -279, "delta_leader_playoff": 0, "delta_chase": -1, "starts": 22, "poles": 1, "wins": 2, "stage_1_wins": 1, "stage_2_wins": 0, "stage_3_wins": 0, "playoff_race_wins": 0, "playoff_stage_wins": 0, "top_5": 7, "top_10": 10, "laps_led": 125, "dnf": 6, "winnings": 0.0, "driver_id": 4327, "driver_first_name": "Sam", "driver_last_name": "Mayer", "driver_suffix": "", "car_no": "1", "manufacturer": "Chevrolet", "delta_playoff": 0, "projected_playoff_points": 2011, "stage_points": 96, "is_clinch": true}, {"position": 5, "driver_name": "AJ Allmendinger", "points": 674, "points_earned": 28, "playoff_points": 674, "playoff_rank": 9, "bonus_points": 0, "delta_next": -30, "delta_leader": -132, "delta_leader_playoff": 0, "delta_chase": -1, "starts": 22, "poles": 0, "wins": 0, "stage_1_wins": 0, "stage_2_wins": 0, "stage_3_wins": 0, "playoff_race_wins": 0, "playoff_stage_wins": 0, "top_5": 3, "top_10": 11, "laps_led": 71, "dnf": 2, "winnings": 0.0, "driver_id": 3774, "driver_first_name": "AJ", "driver_last_name": "Allmendinger", "driver_suffix": "", "car_no": "16", "manufacturer": "Chevrolet", "delta_playoff": 113, "projected_playoff_points": 2006, "stage_points": 170, "is_clinch": false}, {"position": 7, "driver_name": "Sheldon Creed", "points": 654, "points_earned": 40, "playoff_points": 654, "playoff_rank": 10, "bonus_points": 0, "delta_next": -11, "delta_leader": -152, "delta_leader_playoff": 0, "delta_chase": -1, "starts": 22, "poles": 2, "wins": 0, "stage_1_wins": 0, "stage_2_wins": 0, "stage_3_wins": 0, "playoff_race_wins": 0, "playoff_stage_wins": 0, "top_5": 10, "top_10": 14, "laps_led": 49, "dnf": 2, "winnings": 0.0, "driver_id": 4204, "driver_first_name": "Sheldon", "driver_last_name": "Creed", "driver_suffix": "", "car_no": "18", "manufacturer": "Toyota", "delta_playoff": 93, "projected_playoff_points": 2004, "stage_points": 122, "is_clinch": false}]